{
    "ip": "localhost",
    "port": "4843",
    "skill": {
        "name": "Skill_Add",
        "nodeId": "ns=4;i=5012"
    },
    "skillModel": {
        "Description": {
            "name": "Description",
            "nodeId": {
                "ns": "4",
                "nid": "5013"
            },
            "type": "Object"
        },
        "Invokation": {
            "name": "Invokation",
            "nodeId": {
                "ns": "4",
                "nid": "5014"
            },
            "type": "Object",
            "Start": {
                "name": "Start",
                "objectId": {
                    "ns": "4",
                    "nid": "5014"
                },
                "methodId": {
                    "ns": "4",
                    "nid": "7002"
                },
                "type": "Method",
                "parameters": {
                    "inputArguments": [
                        {
                            "name": "Value1",
                            "dataType": "ns=0;i=4",
                            "valueRank": "-1",
                            "arrayDimensions": [
                                "0"
                            ],
                            "id_circle": "f4e79adb-4e56-40e2-8c79-48261e225f05",
                            "id_label": "5472dc07-f19b-42b9-8483-2297af294557",
                            "id_port": "34bbb250-af73-471d-903e-550c4ea6c704"
                        },
                        {
                            "name": "Value2",
                            "dataType": "ns=0;i=4",
                            "valueRank": "-1",
                            "arrayDimensions": [
                                "0"
                            ],
                            "id_circle": "e2564e3c-8f77-417e-b52e-59ca0d8d5b11",
                            "id_label": "8622dae1-9086-4f7b-912c-c83c963b4042",
                            "id_port": "1f4d8be1-941d-4db7-a1aa-2eb29be8c9bb"
                        }
                    ],
                    "outputArguments": ""
                },
                "InputArguments": {
                    "name": "InputArguments",
                    "nodeId": {
                        "ns": "4",
                        "nid": "6097"
                    },
                    "type": "Variable"
                },
                "OutputArguments": {
                    "name": "OutputArguments",
                    "nodeId": {
                        "ns": "4",
                        "nid": "6098"
                    },
                    "type": "Variable"
                }
            },
            "GetResult": {
                "name": "GetResult",
                "objectId": {
                    "ns": "4",
                    "nid": "5014"
                },
                "methodId": {
                    "ns": "4",
                    "nid": "7003"
                },
                "type": "Method",
                "parameters": {
                    "inputArguments": "",
                    "outputArguments": [
                        {
                            "name": "ValueOut",
                            "dataType": "ns=0;i=4",
                            "valueRank": "-1",
                            "arrayDimensions": [
                                "0"
                            ],
                            "id_circle": "c907ad2b-52c8-4686-b934-56a7fb80fbb2",
                            "id_label": "1018c24c-df4b-4b7d-ad2d-2b74efadfcad",
                            "id_port": "20e36a14-5ff0-4586-98df-97a3657ecd0b"
                        }
                    ]
                },
                "InputArguments": {
                    "name": "InputArguments",
                    "nodeId": {
                        "ns": "4",
                        "nid": "6099"
                    },
                    "type": "Variable"
                },
                "OutputArguments": {
                    "name": "OutputArguments",
                    "nodeId": {
                        "ns": "4",
                        "nid": "6100"
                    },
                    "type": "Variable"
                }
            },
            "ResultTrigger": {
                "name": "ResultTrigger",
                "nodeId": {
                    "ns": "4",
                    "nid": "6101"
                },
                "type": "Variable"
            }
        }
    },
    "objectMonitor": {
        "ACTIONS": [
            {
                "name": "Start",
                "objectId": {
                    "ns": "4",
                    "nid": "5014"
                },
                "methodId": {
                    "ns": "4",
                    "nid": "7002"
                },
                "type": "Method",
                "parameters": {
                    "inputArguments": [
                        {
                            "name": "Value1",
                            "dataType": "ns=0;i=4",
                            "valueRank": "-1",
                            "arrayDimensions": [
                                "0"
                            ]
                        },
                        {
                            "name": "Value2",
                            "dataType": "ns=0;i=4",
                            "valueRank": "-1",
                            "arrayDimensions": [
                                "0"
                            ]
                        }
                    ],
                    "outputArguments": ""
                },
                "InputArguments": {
                    "name": "InputArguments",
                    "nodeId": {
                        "ns": "4",
                        "nid": "6097"
                    },
                    "type": "Variable"
                },
                "OutputArguments": {
                    "name": "OutputArguments",
                    "nodeId": {
                        "ns": "4",
                        "nid": "6098"
                    },
                    "type": "Variable"
                }
            },
            {
                "name": "GetResult",
                "objectId": {
                    "ns": "4",
                    "nid": "5014"
                },
                "methodId": {
                    "ns": "4",
                    "nid": "7003"
                },
                "type": "Method",
                "parameters": {
                    "inputArguments": "",
                    "outputArguments": [
                        {
                            "name": "ValueOut",
                            "dataType": "ns=0;i=4",
                            "valueRank": "-1",
                            "arrayDimensions": [
                                "0"
                            ]
                        }
                    ]
                },
                "InputArguments": {
                    "name": "InputArguments",
                    "nodeId": {
                        "ns": "4",
                        "nid": "6099"
                    },
                    "type": "Variable"
                },
                "OutputArguments": {
                    "name": "OutputArguments",
                    "nodeId": {
                        "ns": "4",
                        "nid": "6100"
                    },
                    "type": "Variable"
                }
            }
        ]
    },
    "version": "V3",
    "parameters": {
        "inputs": [
            {
                "name": "Value1",
                "dataType": "ns=0;i=4",
                "valueRank": "-1",
                "arrayDimensions": [
                    "0"
                ],
                "id_circle": "f4e79adb-4e56-40e2-8c79-48261e225f05",
                "id_label": "5472dc07-f19b-42b9-8483-2297af294557",
                "id_port": "34bbb250-af73-471d-903e-550c4ea6c704"
            },
            {
                "name": "Value2",
                "dataType": "ns=0;i=4",
                "valueRank": "-1",
                "arrayDimensions": [
                    "0"
                ],
                "id_circle": "e2564e3c-8f77-417e-b52e-59ca0d8d5b11",
                "id_label": "8622dae1-9086-4f7b-912c-c83c963b4042",
                "id_port": "1f4d8be1-941d-4db7-a1aa-2eb29be8c9bb"
            }
        ],
        "outputs": [
            {
                "name": "ValueOut",
                "dataType": "ns=0;i=4",
                "valueRank": "-1",
                "arrayDimensions": [
                    "0"
                ],
                "id_circle": "c907ad2b-52c8-4686-b934-56a7fb80fbb2",
                "id_label": "1018c24c-df4b-4b7d-ad2d-2b74efadfcad",
                "id_port": "20e36a14-5ff0-4586-98df-97a3657ecd0b"
            }
        ]
    }
}